primaryschool/__init__.py
primaryschool/settings.py
primaryschool/settings.txt
primaryschool/settings_t.py
primaryschool/dirs/__init__.py
primaryschool/exception/__init__.py
primaryschool/games/__init__.py
primaryschool/implements/__init__.py
primaryschool/locale/__init__.py
primaryschool/locale/en_US/LC_MESSAGES/primaryschool.mo
primaryschool/locale/zh_CN/LC_MESSAGES/primaryschool.mo
primaryschool/ready/__init__.py
primaryschool/ready/_abc_.py
primaryschool/ready/abc.py
primaryschool/ready/common.py
primaryschool/ready/psready.py
primaryschool/resource/__init__.py
primaryschool/resource/imgs/0x1.png
primaryschool/resource/imgs/0x4.png
primaryschool/subjects/__init__.py
primaryschool/subjects/_abc_.py
primaryschool/subjects/_common_/__init__.py
primaryschool/subjects/_common_/keycode.py
primaryschool/subjects/_common_/shootingbase.py
primaryschool/subjects/_common_/media/__init__.py
primaryschool/subjects/_common_/media/img/0x0.png
primaryschool/subjects/_common_/media/img/0x1.png
primaryschool/subjects/english/__init__.py
primaryschool/subjects/english/g_chinese_english_missile/__init__.py
primaryschool/subjects/english/g_chinese_english_missile/words.py
primaryschool/subjects/english/g_chinese_english_missile/media/__init__.py
primaryschool/subjects/english/media/__init__.py
primaryschool/subjects/math/__init__.py
primaryschool/subjects/math/g_mind_hunter/__init__.py
primaryschool/subjects/math/g_mind_hunter/media/__init__.py
primaryschool/subjects/math/media/__init__.py
primaryschool/subjects/media/__init__.py
primaryschool/subjects/media/img/0x0.png
primaryschool/subjects/media/img/0x1.png
primaryschool/subjects/media/img/0x2.png
primaryschool/subjects/media/img/0x3.png
primaryschool/subjects/yuwen/__init__.py
primaryschool/subjects/yuwen/words.py
primaryschool/subjects/yuwen/yumu.py
primaryschool/subjects/yuwen/g_pinyin_missile/__init__.py
primaryschool/subjects/yuwen/g_pinyin_missile/media/__init__.py
primaryschool/subjects/yuwen/media/__init__.py
primaryschool-0.0.25.dist-info/LICENSE
primaryschool-0.0.25.dist-info/METADATA
primaryschool-0.0.25.dist-info/WHEEL
primaryschool-0.0.25.dist-info/entry_points.txt
primaryschool-0.0.25.dist-info/top_level.txt
primaryschool-0.0.25.dist-info/RECORD
