Metadata-Version: 2.1
Name: primaryschool
Version: 0.0.25
Summary: primary school knowledge games
Home-page: https://github.com/larryw3i/primaryschool
Author: larryw3i
Author-email: larryw3i@163.com
Maintainer: larryw3i
Maintainer-email: larryw3i@163.com
License: UNKNOWN
Platform: UNKNOWN
Classifier: Programming Language :: Python :: 3
Classifier: License :: OSI Approved :: MIT License
Classifier: Operating System :: OS Independent
Requires-Python: >=3.6
License-File: LICENSE
Requires-Dist: pygame
Requires-Dist: pygame-menu
Requires-Dist: xpinyin
Requires-Dist: appdirs
